{
  "date": "2026-06-27",
  "question": {
    "title": "Ranking Sales by Region",
    "difficulty": "Medium",
    "topic": "Window Functions",
    "desc": "Write a SQL query to rank sales representatives by their total sales amount within each region, using window functions. The output should include the representative's name, their region, and their rank based on sales.",
    "setup": "DROP TABLE IF EXISTS sales_representatives; CREATE TABLE sales_representatives (name VARCHAR(50), region VARCHAR(50), sales DECIMAL(10, 2)); INSERT INTO sales_representatives (name, region, sales) VALUES ('John Doe', 'North', 10000.00), ('Jane Doe', 'North', 8000.00), ('Alice Smith', 'South', 12000.00), ('Bob Johnson', 'South', 9000.00), ('Charlie Brown', 'East', 11000.00), ('David Lee', 'East', 7000.00);",
    "tables": [
      "sales_representatives"
    ],
    "cols": [
      "name",
      "region",
      "rank"
    ],
    "rows": [
      [
        "Charlie Brown",
        "East",
        1
      ],
      [
        "David Lee",
        "East",
        2
      ],
      [
        "Alice Smith",
        "South",
        1
      ],
      [
        "Bob Johnson",
        "South",
        2
      ],
      [
        "John Doe",
        "North",
        1
      ],
      [
        "Jane Doe",
        "North",
        2
      ]
    ],
    "solution": "SELECT name, region, RANK() OVER (PARTITION BY region ORDER BY sales DESC) AS rank FROM sales_representatives;",
    "tips": "Using PARTITION BY allows the window function to reset for each group, and RANK() assigns a rank based on the ORDER BY clause.",
    "hints": [
      "Consider using a window function that can partition the data by region and then rank based on sales.",
      "You will need to use the OVER clause with PARTITION BY to divide the data into regions before ranking.",
      "The correct query will use RANK() OVER (PARTITION BY region ORDER BY sales DESC) to achieve the desired ranking."
    ],
    "tests": [
      {
        "setup": "DROP TABLE IF EXISTS sales_representatives; CREATE TABLE sales_representatives (name VARCHAR(50), region VARCHAR(50), sales DECIMAL(10, 2)); INSERT INTO sales_representatives (name, region, sales) VALUES ('Eve Williams', 'West', 13000.00), ('Frank Davis', 'West', 10000.00), ('Grace Hall', 'Central', 14000.00), ('Helen Martin', 'Central', 11000.00);",
        "rows": [
          [
            "Grace Hall",
            "Central",
            1
          ],
          [
            "Helen Martin",
            "Central",
            2
          ],
          [
            "Eve Williams",
            "West",
            1
          ],
          [
            "Frank Davis",
            "West",
            2
          ]
        ]
      },
      {
        "setup": "DROP TABLE IF EXISTS sales_representatives; CREATE TABLE sales_representatives (name VARCHAR(50), region VARCHAR(50), sales DECIMAL(10, 2)); INSERT INTO sales_representatives (name, region, sales) VALUES ('Isaac Kim', 'North', 15000.00), ('Julia Patel', 'North', 12000.00), ('Kevin White', 'South', 16000.00), ('Lily Chen', 'South', 14000.00);",
        "rows": [
          [
            "Kevin White",
            "South",
            1
          ],
          [
            "Lily Chen",
            "South",
            2
          ],
          [
            "Isaac Kim",
            "North",
            1
          ],
          [
            "Julia Patel",
            "North",
            2
          ]
        ]
      }
    ]
  }
}
